.DS_Store
TSMovieComposer/__init__.py
TSMovieComposer/composer.py
TSMovieComposer/main.py
TSMovieComposer/parser.py
TSMovieComposer/player.py
TSMovieComposer/playground.py
flavtool/__init__.py
flavtool/analyzer/__init__.py
flavtool/analyzer/analyze.py
flavtool/analyzer/flavMp4.py
flavtool/analyzer/components/__init__.py
flavtool/analyzer/components/components.py
flavtool/analyzer/media_data/__init__.py
flavtool/analyzer/media_data/chunk.py
flavtool/analyzer/media_data/media_data.py
flavtool/analyzer/media_data/sample.py
flavtool/codec/__init__.py
flavtool/codec/codec_options.py
flavtool/codec/decoder.py
flavtool/codec/encoder.py
flavtool/composer/__init__.py
flavtool/composer/composer.py
flavtool/composer/utils/__init__.py
flavtool/composer/utils/empty_mp4_creator.py
flavtool/composer/utils/sample_table_creator.py
flavtool/composer/utils/track_box_creator.py
flavtool/logger/__init__.py
flavtool/parser/__init__.py
flavtool/parser/_parser.py
flavtool/parser/boxs/__init__.py
flavtool/parser/boxs/box.py
flavtool/parser/boxs/container.py
flavtool/parser/boxs/leaf.py
flavtool-0.1.1.dist-info/METADATA
flavtool-0.1.1.dist-info/WHEEL
flavtool-0.1.1.dist-info/top_level.txt
flavtool-0.1.1.dist-info/RECORD
