Metadata-Version: 2.1
Name: flavtool
Version: 0.1.1
Summary: 味覚情報を埋め込み可能なファイル形式:FlavMP4の解析、編集を可能にするツールキット
Home-page: https://github.com/hmwri/flavtool
Author: Taiyu Honma
Author-email: ev220526@meiji.ac.jp
Classifier: Programming Language :: Python :: 3.7
Classifier: License :: OSI Approved :: MIT License
Classifier: Operating System :: OS Independent
